microsoft_agents/copilotstudio/client/__init__.py
microsoft_agents/copilotstudio/client/agent_type.py
microsoft_agents/copilotstudio/client/connection_settings.py
microsoft_agents/copilotstudio/client/copilot_client.py
microsoft_agents/copilotstudio/client/direct_to_engine_connection_settings_protocol.py
microsoft_agents/copilotstudio/client/execute_turn_request.py
microsoft_agents/copilotstudio/client/power_platform_cloud.py
microsoft_agents/copilotstudio/client/power_platform_environment.py
microsoft_agents_copilotstudio_client-0.3.2.dist-info/METADATA
microsoft_agents_copilotstudio_client-0.3.2.dist-info/WHEEL
microsoft_agents_copilotstudio_client-0.3.2.dist-info/top_level.txt
microsoft_agents_copilotstudio_client-0.3.2.dist-info/RECORD
